easy_ec2/__init__.py
easy_ec2/cloudwatch/__init__.py
easy_ec2/cloudwatch/cloudwatch.py
easy_ec2/cloudwatch/create.py
easy_ec2/cloudwatch/delete.py
easy_ec2/cloudwatch/list.py
easy_ec2/compound.py
easy_ec2/ec2/__init__.py
easy_ec2/ec2/config_parser.py
easy_ec2/ec2/connect.py
easy_ec2/ec2/create.py
easy_ec2/ec2/ec2.py
easy_ec2/ec2/ec2_connections_management.py
easy_ec2/ec2/ec2_instance_management.py
easy_ec2/ec2/list.py
easy_ec2/ec2/logs.py
easy_ec2/ec2/script.py
easy_ec2/ec2/ssh.py
easy_ec2/ec2/start.py
easy_ec2/ec2/stop.py
easy_ec2/ec2/stop_all.py
easy_ec2/ec2/terminate.py
easy_ec2/main.py
easy_ec2/profile/__init__.py
easy_ec2/profile/active.py
easy_ec2/profile/ownership.py
easy_ec2/profile/profile.py
easy_ec2/profile/validation.py
easy_ec2/router.py
easy_ec2/setup_session.py
easy_ec2/utilities/__init__.py
easy_ec2/utilities/aws_profile_parser.py
easy_ec2/utilities/decorators.py
easy_ec2/utilities/logger_maker.py
easy_ec2-0.1.9.dist-info/LICENSE
easy_ec2-0.1.9.dist-info/METADATA
easy_ec2-0.1.9.dist-info/WHEEL
easy_ec2-0.1.9.dist-info/entry_points.txt
easy_ec2-0.1.9.dist-info/RECORD
